premailer/__init__.py
premailer/__main__.py
premailer/cache.py
premailer/merge_style.py
premailer/premailer.py
premailer-3.9.0.dist-info/LICENSE
premailer-3.9.0.dist-info/METADATA
premailer-3.9.0.dist-info/WHEEL
premailer-3.9.0.dist-info/top_level.txt
premailer-3.9.0.dist-info/RECORD
